run_tracker/__init__.py
run_tracker/run_tracker.py
run_tracker/utils.py
script_run_tracker-0.1.4.dist-info/licenses/LICENSE
tests/__init__.py
tests/test_script_run_tracker.py
script_run_tracker-0.1.4.dist-info/METADATA
script_run_tracker-0.1.4.dist-info/WHEEL
script_run_tracker-0.1.4.dist-info/top_level.txt
script_run_tracker-0.1.4.dist-info/RECORD
