Metadata-Version: 2.4
Name: script-run-tracker
Version: 0.1.4
Summary: A lightweight SQLite-based run tracker for Python scripts
Home-page: https://github.com/domiterd/run_tracker
Author: Dominik Domiter
Author-email: Dominik Domiter <dominik.domiter@autowallis.hu>
License: MIT
Project-URL: Homepage, https://github.com/domiterd/script-run-tracker
Project-URL: Bug Reports, https://github.com/domiterd/script-run-tracker/issues
Project-URL: Source, https://github.com/domiterd/script-run-tracker
Keywords: logging,tracking,sqlite,scheduler,monitoring
Classifier: Programming Language :: Python :: 3
Classifier: Programming Language :: Python :: 3.7
Classifier: Programming Language :: Python :: 3.8
Classifier: Programming Language :: Python :: 3.9
Classifier: Programming Language :: Python :: 3.10
Classifier: Programming Language :: Python :: 3.11
Classifier: License :: OSI Approved :: MIT License
Classifier: Operating System :: OS Independent
Requires-Python: >=3.7
License-File: LICENSE
Dynamic: author
Dynamic: home-page
Dynamic: license-file
Dynamic: requires-python
